<?xml version="1.0" encoding="utf-8" ?>
<dwsync>
<file name="bg.png" server="C:/xampp/htdocs/firebasecrud/" local="132931747610000000" remote="132931747610000000" />
<file name="brand.png" server="C:/xampp/htdocs/firebasecrud/" local="132931747610000000" remote="132931747610000000" />
<file name="profile.jpg" server="C:/xampp/htdocs/firebasecrud/" local="132931747610000000" remote="132931747610000000" />
<file name="bg.png" server="C:/xampp/htdocs/emventory/" local="133276020773366974" remote="133276020770000000" />
<file name="brand.png" server="C:/xampp/htdocs/emventory/" local="132931747610000000" remote="132931747610000000" />
<file name="1.png" server="C:/xampp/htdocs/emventory/" local="132931747610000000" remote="132931747610000000" />
<file name="2.png" server="C:/xampp/htdocs/emventory/" local="132931747610000000" remote="132931747610000000" />
<file name="3.png" server="C:/xampp/htdocs/emventory/" local="132931747610000000" remote="132931747610000000" />
<file name="4.png" server="C:/xampp/htdocs/emventory/" local="132931747610000000" remote="132931747610000000" />
<file name="5.png" server="C:/xampp/htdocs/emventory/" local="132931747610000000" remote="132931747610000000" />
<file name="6.png" server="C:/xampp/htdocs/emventory/" local="132931747610000000" remote="132931747610000000" />
<file name="profile.jpg" server="C:/xampp/htdocs/emventory/" local="133281810080312496" remote="133281810080000000" />
<file name="profile.png" server="C:/xampp/htdocs/emventory/" local="133281813183945312" remote="133281813180000000" />
</dwsync>